pyproffit/__init__.py
pyproffit/data.py
pyproffit/deproject.py
pyproffit/emissivity.py
pyproffit/fitting.py
pyproffit/hmc.py
pyproffit/miscellaneous.py
pyproffit/models.py
pyproffit/power_spectrum.py
pyproffit/profextract.py
pyproffit/radio.py
pyproffit/reload.py
pyproffit-0.8.dist-info/LICENSE
pyproffit-0.8.dist-info/METADATA
pyproffit-0.8.dist-info/WHEEL
pyproffit-0.8.dist-info/top_level.txt
pyproffit-0.8.dist-info/RECORD
