Metadata-Version: 2.1
Name: pyproffit
Version: 0.8
Summary: Python package for PROFFIT
Home-page: https://github.com/domeckert/pyproffit
Author: Dominique Eckert
Author-email: Dominique.Eckert@unige.ch
License-File: LICENSE
Requires-Dist: numpy
Requires-Dist: scipy
Requires-Dist: astropy
Requires-Dist: matplotlib
Requires-Dist: iminuit
Requires-Dist: pymc
